polympics/__init__.py
polympics/clients.py
polympics/handlers.py
polympics/pagination.py
polympics/types.py
polympics-0.6.2.dist-info/LICENSE
polympics-0.6.2.dist-info/METADATA
polympics-0.6.2.dist-info/WHEEL
polympics-0.6.2.dist-info/top_level.txt
polympics-0.6.2.dist-info/RECORD
