Metadata-Version: 2.1
Name: polympics
Version: 0.6.2
Summary: A Python wrapper for the Polympics API.
Home-page: https://github.com/polympics/python-wrapper
Author: Artemis
Author-email: artemisdev21@gmail.com
License: UNKNOWN
Platform: UNKNOWN
Classifier: Programming Language :: Python :: 3
Classifier: License :: OSI Approved :: MIT License
Classifier: Operating System :: OS Independent
Requires-Python: >=3.9
License-File: LICENSE
Requires-Dist: aiohttp
Requires-Dist: dataclasses-json
